eleran/__init__.py
eleran/__main__.py
eleran/main.py
eleran/version.py
eleran-1.0.1.dist-info/METADATA
eleran-1.0.1.dist-info/RECORD
eleran-1.0.1.dist-info/WHEEL
eleran-1.0.1.dist-info/entry_points.txt
eleran-1.0.1.dist-info/top_level.txt
eleran-1.0.1.dist-info/zip-safe
