Metadata-Version: 2.1
Name: eleran
Version: 1.0.1
Summary: Simple & fast sass compiler and javascript minifier with hot reloading
Home-page: https://github.com/bapakode/eleran
Author: Bapakode Open Source
Author-email: opensource@bapakode.com
License: MIT
Platform: UNKNOWN
Classifier: Development Status :: 3 - Alpha
Classifier: Environment :: Console
Classifier: Programming Language :: Python
Classifier: Programming Language :: Python :: 3
Classifier: Programming Language :: Python :: 3 :: Only
Classifier: Programming Language :: Python :: 3.5
Classifier: Programming Language :: Python :: 3.6
Classifier: Intended Audience :: Developers
Classifier: Intended Audience :: Information Technology
Classifier: Intended Audience :: System Administrators
Classifier: License :: OSI Approved :: MIT License
Classifier: Operating System :: Unix
Classifier: Operating System :: POSIX :: Linux
Classifier: Environment :: MacOS X
Classifier: Topic :: Software Development :: Libraries :: Python Modules
Requires-Python: >=3.5
Requires-Dist: click (==6.7)
Requires-Dist: libsass (==0.14.5)
Requires-Dist: watchgod (==0.2)
Requires-Dist: jsmin (==2.2.2)
